[{"cat":1000,"sec":1,"com":"Lecture","sub":"BIOL","num":1375,"nam":"Gen Biology","enr":120,"des":"Biology as a modern science stressing organization, genetic control, development, ecological interrelationships, evolution, physiology, and behavior.","cap":134,"typ":"In Person","uni":"--","ins":[["BRAUN, T.","u0058958"]],"gen":["SF"],"yea":2001,"sem":8},{"cat":1000,"sec":4,"com":"Lecture","sub":"BIOL","num":1376,"nam":"Gen Biology","enr":235,"des":"Biology as a modern science stressing organization, genetic control, development, ecological interrelationships, evolution, physiology, and behavior.","cap":234,"typ":"In Person","uni":"--","ins":[["TEMME, D. H.","u0030846"]],"gen":["SF"],"yea":2001,"sem":8},{"cat":1000,"sec":5,"com":"Lecture","sub":"BIOL","num":4345,"nam":"Gen Biology","enr":224,"des":"Biology as a modern science stressing organization, genetic control, development, ecological interrelationships, evolution, physiology, and behavior.","cap":234,"typ":"In Person","uni":"--","ins":[["TEMME, D. H.","u0030846"]],"gen":["SF"],"yea":2001,"sem":8},{"cat":1000,"sec":6,"com":"Lecture","sub":"BIOL","num":12950,"nam":"Gen Biology","enr":83,"des":"Biology as a modern science stressing organization, genetic control, development, ecological interrelationships, evolution, physiology, and behavior.","cap":150,"typ":"In Person","uni":"4.0","ins":[["VICKERS, T. M.","u0139137"]],"gen":["SF"],"yea":2001,"sem":8},{"cat":1000,"sec":20,"com":"Lecture","sub":"BIOL","num":13977,"nam":"Gen Biology","enr":16,"des":"Biology as a modern science stressing organization, genetic control, development, ecological interrelationships, evolution, physiology, and behavior.","cap":35,"typ":"In Person","uni":"4.0","ins":[["BRAUN, T.","u0058958"]],"att":["Continuing Education"],"gen":["AOCE","SF"],"yea":2001,"sem":8},{"cat":1400,"sec":1,"com":"Lecture","sub":"BIOL","num":1380,"nam":"Intr Envirnmntl Science","enr":80,"des":"Introduction to ecological principles that underlie environmental science and natural resource conservation. Examination of the environment as the context for human activities. Discussion of human effects on ecosystems.","cap":134,"typ":"In Person","uni":"--","ins":[["MONTAGUE JR, F. H.","u0029415"]],"gen":["SF"],"yea":2001,"sem":8},{"cat":2020,"sec":1,"com":"Lecture","sub":"BIOL","num":9927,"nam":"Princ of Cell Biology","enr":328,"des":"Structure of cells and organelles in prokaryotes and eukaryotes, function of cellular components, cell shape and movement, and differentiation and development in cell systems.","cap":348,"typ":"In Person","uni":"--","ins":[["GARD, D. L.","u0034654"],["KROPF, D. L.","u0035054"]],"req":["Prerequisite: BIOL 1210 (or equivalent) and BIOL 2010, and CHEM 1210."],"rek":"Yes","syl":"http:\/\/courses.biology.utah.edu\/gard\/cell\/","yea":2001,"sem":8},{"cat":2030,"sec":1,"com":"Lecture","sub":"BIOL","num":9928,"nam":"Genetics","enr":108,"des":"Study of classical genetics including the rules of inheritance, transmission genetics, and genes in populations. Also covers molecular analysis of gene structure, function, expression, and evolution.","cap":348,"typ":"In Person","uni":"--","ins":[["ROTH, J. R.","u0030438"],["SEGER, J.","u0034759"]],"req":["Prerequisite: BIOL 2020 or instructor's consent."],"rek":"Yes","yea":2001,"sem":8},{"cat":2315,"sec":1,"com":"Lecture","sub":"BIOL","num":1388,"nam":"Human Anatomy","enr":350,"des":"Rigorous, in-depth coverage of structure and function of the human body. Laboratories use prosected human body parts.","cap":348,"typ":"In Person","uni":"--","ins":[["NIELSEN, M. T.","u0032875"]],"req":["Recommended Prerequisite: BIOL 1210 or 1320."],"fee":"$45.00","rek":"Yes","yea":2001,"sem":8},{"cat":2320,"sec":1,"com":"Lecture","sub":"BIOL","num":3299,"nam":"Human Physiology","enr":163,"des":"Principles of human function.","cap":348,"typ":"In Person","uni":"4.0","ins":[["MUEHLEISEN, D. P.","u0028581"]],"req":["Recommended Prerequisite: CHEM 1210 and BIOL 1210 or equivalent."],"rek":"Yes","yea":2001,"sem":8},{"cat":2320,"sec":3,"com":"Lecture","sub":"BIOL","num":11964,"nam":"Human Physiology","enr":78,"des":"Principles of human function.","cap":104,"typ":"In Person","uni":"4.0","ins":[["MUEHLEISEN, D. P.","u0028581"]],"req":["Recommended Prerequisite: CHEM 1210 and BIOL 1210 or equivalent."],"rek":"Yes","yea":2001,"sem":8},{"cat":2320,"sec":5,"com":"Lecture","sub":"BIOL","num":12791,"nam":"Human Physiology","enr":39,"des":"Principles of human function.","cap":134,"typ":"In Person","uni":"4.0","ins":[["MUEHLEISEN, D. P.","u0028581"]],"req":["Recommended Prerequisite: CHEM 1210 and BIOL 1210 or equivalent."],"rek":"Yes","yea":2001,"sem":8},{"cat":2400,"sec":1,"com":"Lecture","sub":"BIOL","num":1391,"nam":"Princ Wldlf Ecol Consrv","enr":53,"des":"Wildlife population principles and habitat relationships. Current wildlife management practices and research techniques. Human effects on wildlife populations.","cap":134,"typ":"In Person","uni":"--","ins":[["MONTAGUE JR, F. H.","u0029415"]],"gen":["SI"],"yea":2001,"sem":8},{"cat":2870,"sec":1,"com":"Seminar","sub":"BIOL","num":1393,"nam":"Faculty Research Sem","enr":24,"des":"Open to all undergraduates. Familiarizes students with faculty research in all areas of biological science.","cap":40,"typ":"In Person","uni":"--","ins":[["GRAY, R.","u0028842"]],"yea":2001,"sem":8},{"cat":3080,"sec":1,"com":"Lecture","sub":"BIOL","num":3162,"nam":"Predental Orientation","enr":71,"des":"Basic course in dental terminology, tooth morphology, materials, and instrument handling. Overview of dental college and dental profession.","cap":77,"typ":"In Person","uni":"--","ins":[["MIRCI, J. G.","u0035433"]],"fee":"$90.00","yea":2001,"sem":8},{"cat":3115,"sec":1,"com":"Lecture","sub":"BIOL","num":6310,"nam":"Cmptr Appl Cell Bio Lab","enr":0,"des":"Fundamentals of electronic and optical instruments used in biological research, and the use of the computer to acquire, process, and display data from instruments, applied principally in cell-physiology experiments.","cap":0,"typ":"In Person","uni":"--","req":["Recommended Prerequsite: BIOL 2020 and PHYCS 2020."],"fee":"$65.00","rek":"Yes","yea":2001,"sem":8},{"cat":3215,"sec":1,"com":"Lecture","sub":"BIOL","num":2054,"nam":"Cell Lab","enr":34,"des":"Experimental analysis of cell structure and function. Note: students may enroll concurrently in BIOL 5215 and carry out more extensive and independent experiments.","cap":24,"typ":"In Person","uni":"--","ins":[["GRAY, R.","u0028842"]],"req":["Recommended Prerequisite: BIOL 2020."],"fee":"$70.00","rek":"Yes","yea":2001,"sem":8},{"cat":3240,"sec":1,"com":"Lecture","sub":"BIOL","num":1397,"nam":"Intro Cell Neurobiology","enr":0,"des":"Introduction to the anatomy, physiology, and chemistry of nervous systems at the cellular level.","cap":0,"typ":"In Person","uni":"--","req":["Recommended Prerequsite: BIOL 2020 and PHYCS 2020."],"rek":"Yes","yea":2001,"sem":8},{"cat":3245,"sec":1,"com":"Lecture","sub":"BIOL","num":4351,"nam":"Cell Neurobiology Lab","enr":0,"des":"Methods and instrumentation of neurobiology; emphasizes electrophysiology with computerized data acquisition and control.","cap":0,"typ":"In Person","uni":"--","req":["Recommended Prerequisite: BIOL 3240 or Co-requisite."],"fee":"$65.00","rek":"Yes","yea":2001,"sem":8},{"cat":3310,"sec":1,"com":"Lecture","sub":"BIOL","num":9931,"nam":"Comparative Vert Morph","enr":67,"des":"Evolution of vertebrate structure with emphasis on current functional and evolutionary interpretations. Introduction to vertebrate biomechanics.","cap":134,"typ":"In Person","uni":"--","ins":[["BRAMBLE, D. M.","u0034749"]],"req":["Recommended Prerequisite: BIOL 2010 and 2020."],"rek":"Yes","yea":2001,"sem":8},{"cat":3320,"sec":1,"com":"Lecture","sub":"BIOL","num":12792,"nam":"Compar Physiol","enr":93,"des":"Physiological mechanisms of animals with emphasis on vertebrates: Neural and hormonal control, musculoskeletal function, cardiopulmonary function, energetics, thermoregulation, and osmoregulation.","cap":134,"typ":"In Person","uni":"3.0","ins":[["GOLLER, F.","u0101753"]],"req":["Recommended Prerequisite: BIOL 2010."],"rek":"Yes","yea":2001,"sem":8},{"cat":3330,"sec":1,"com":"Lecture","sub":"BIOL","num":9934,"nam":"Behav Neurobiology","enr":53,"des":"This course will provide a basic understanding of issues such as: 1) how information is acquired by sensory systems, coded and processed by the central nervous system, 2) how sensory information is translated to motor commands, 3) motor pattern generation, 4) role of experience in shaping organization of brain.","cap":134,"typ":"In Person","uni":"--","ins":[["ROSE, G. J.","u0034951"]],"req":["Recommended Prerequisite: BIOL 2010."],"rek":"Yes","yea":2001,"sem":8},{"cat":3415,"sec":1,"com":"Lecture","sub":"BIOL","num":9935,"nam":"Ecol Lab","enr":18,"des":"Generation and testing of ecological hypotheses in laboratory and field experiments. Topics include species variation and natural history, mimicry and frequency dependence, plant chemistry and herbivory, predator-prey dynamics, and competition models.","cap":24,"typ":"In Person","uni":"--","ins":[["DEARING, M. D.","u0028665"]],"req":["Prerequisite: BIOL 2010."],"rek":"Yes","yea":2001,"sem":8},{"cat":3510,"sec":1,"com":"Lecture","sub":"BIOL","num":3164,"nam":"Biological Chemistry I","enr":86,"des":"Structure and function of biomolecules, metabolism, and regulation.","cap":130,"typ":"In Person","uni":"--","ins":[["GRISSOM, C. B.","u0035127"]],"req":["Prerequisite: BIOL 2020, 2030, CHEM 2320."],"rek":"Yes","yea":2001,"sem":8},{"cat":4876,"sec":1,"com":"Seminar","sub":"BIOL","num":3165,"nam":"Journal Club Seminar","enr":38,"des":"Students present seminars from current literature in biological research.","cap":45,"typ":"In Person","uni":"--","ins":[["GRAY, R.","u0028842"]],"yea":2001,"sem":8},{"cat":4950,"sec":1,"com":"Lecture","sub":"BIOL","num":3166,"nam":"Directed Reading","enr":0,"des":"Topics by arrangement with individual faculty chosen by student.","cap":10,"typ":"In Person","uni":"--","ins":[["PARKINSON JR, J. S.","u0028873"]],"yea":2001,"sem":8},{"cat":4955,"sec":1,"com":"Lecture","sub":"BIOL","num":7408,"nam":"Individual Research","enr":0,"des":"Research credit by student arrangement with individual faculty and Biology Advising Office.","cap":10,"typ":"In Person","uni":"--","ins":[["PARKINSON JR, J. S.","u0028873"]],"yea":2001,"sem":8},{"cat":4955,"sec":68,"com":"Lecture","sub":"BIOL","num":14091,"nam":"Individual Research","enr":4,"des":"Research credit by student arrangement with individual faculty and Biology Advising Office.","cap":5,"typ":"In Person","uni":"1.0 - 12.0","ins":[["TORTI, S. D.","u0029263"]],"yea":2001,"sem":8},{"cat":4999,"sec":1,"com":"Lecture","sub":"BIOL","num":9239,"nam":"Hon Thesis\/Project","enr":1,"des":"Restricted to students in the Honors Program working on their Honors degree.","cap":10,"typ":"In Person","uni":"--","ins":[["KROPF, D. L.","u0035054"]],"att":["Honors Course"],"req":["Prerequisite: Restricted to Honors College."],"gen":["HON","CW"],"rek":"Yes","yea":2001,"sem":8},{"cat":5110,"sec":1,"com":"Lecture","sub":"BIOL","num":1404,"nam":"Molec Biol\/Gen Eng","enr":0,"des":"Recombinant-DNA principles and techniques; background biology. Basic enzymology of DNA (restriction and modification, sealing, reverse transcription, nick translation, end labeling, etc.), cloning plasmids and their replication, bacteriophage, and basic methodologies.","cap":0,"typ":"In Person","uni":"--","req":["Recommended Prerequisite: BIOL 3510 or CHEM 3510."],"rek":"Yes","yea":2001,"sem":8},{"cat":5312,"sec":1,"com":"Lecture","sub":"BIOL","num":1410,"nam":"Human Dissection","enr":5,"des":"General dissections of adult human cadavers; preparation of specific prosections for didactic purposes.","cap":25,"typ":"In Person","uni":"--","ins":[["NIELSEN, M. T.","u0032875"]],"req":["Instructor Consent"],"rek":"Yes","yea":2001,"sem":8},{"cat":5313,"sec":1,"com":"Lecture","sub":"BIOL","num":1412,"nam":"Teaching Anatomy","enr":31,"des":"Credit for experience as teaching assistant or teaching apprentice in BIOL 231.","cap":40,"typ":"In Person","uni":"--","ins":[["NIELSEN, M. T.","u0032875"]],"req":["Prerequisite: BIOL 2325 or instructor's consent."],"rek":"Yes","yea":2001,"sem":8},{"cat":5314,"sec":1,"com":"Lecture","sub":"BIOL","num":1414,"nam":"Anatomy Colloquium","enr":38,"des":"Presentation and discussion of advanced topics in vertebrate- human anatomy and morphogenesis. Experience as anatomy teaching assistant or apprentice required.","cap":134,"typ":"In Person","uni":"--","ins":[["NIELSEN, M. T.","u0032875"]],"req":["Instructor Consent"],"rek":"Yes","yea":2001,"sem":8},{"cat":5460,"sec":1,"com":"Lecture","sub":"BIOL","num":9944,"nam":"Plant Ecology","enr":75,"des":"Adaptive physiology and structure\/function relationships between plants and their environments. Microclimate, energy balance, life-history, competition, and carbon, water, and nutrient relations of plants in different ecosystems. Focus also on the diversity of global plant communities.","cap":134,"typ":"In Person","uni":"--","ins":[["EHLERINGER, J. R.","u0034952"]],"req":["Recommended Prerequisite: BIOL 2010."],"rek":"Yes","yea":2001,"sem":8},{"cat":5471,"sec":1,"com":"Lecture","sub":"BIOL","num":12794,"nam":"Fun Method Evol Ecology","enr":7,"des":"Meets with ANTHR 4471; additional work required of graduate students. See ANTHR 4471 for course description.","cap":10,"typ":"In Person","uni":"3.0","ins":[["ROGERS, A. R.","u0028949"]],"req":["Prerequisite: Graduate standing required; Both BIOL 3410 or equivalent, and MATH 1050 or equivalent."],"rek":"Yes","yea":2001,"sem":8},{"cat":5900,"sec":1,"com":"Lecture","sub":"BIOL","num":3172,"nam":"Tchg Experience","enr":2,"des":"Repeatable for up to six credit hours. Credit will not be awarded for teaching the same course more than twice. Contact Biology Advising Office for information. Experience in teaching laboratory, discussion, or quiz sections. Arrangements should be made with professor in charge of course.","cap":100,"typ":"In Person","uni":"--","ins":[["WOLSTENHOLME, D. R.","u0029503"]],"req":["Instructor Consent"],"rek":"Yes","yea":2001,"sem":8},{"cat":5910,"sec":1,"com":"Lecture","sub":"BIOL","num":12793,"nam":"Math Models In Biol","enr":14,"des":"Various techniques of mathematical modelling of a range of biological systems, including ecology, physiology, cell biology, and genetics.","cap":20,"typ":"In Person","uni":"2.0","ins":[["ADLER, F. R.","u0028684"]],"req":["Prerequisite: Either both MATH 1210 and 1220 or both MATH 1170 and 1180."],"gen":["QI"],"rek":"Yes","yea":2001,"sem":8},{"cat":5960,"sec":1,"com":"Lecture","sub":"BIOL","num":14409,"nam":"Atmosph CO2 & Bio Sys","enr":5,"des":"Topics of special interest taught when justified by student and faculty interest. Content varies from year to year.","cap":5,"typ":"In Person","uni":"1.0 - 5.0","ins":[["CERLING, T. E.","u0029442"],["DEARING, M. D.","u0028665"],["EHLERINGER, J. R.","u0034952"]],"yea":2001,"sem":8},{"cat":5960,"sec":2,"com":"Lecture","sub":"BIOL","num":14469,"nam":"Adv Spec Tpcs In Biol","enr":1,"des":"Topics of special interest taught when justified by student and faculty interest. Content varies from year to year.","cap":1,"typ":"In Person","uni":"1.0 - 5.0","ins":[["FEENER JR, D. H.","u0035405"]],"yea":2001,"sem":8},{"cat":5960,"sec":3,"com":"Lecture","sub":"BIOL","num":14497,"nam":"Comp Vert Morphology","enr":2,"des":"Topics of special interest taught when justified by student and faculty interest. Content varies from year to year.","cap":2,"typ":"In Person","uni":"1.0 - 5.0","ins":[["BRAMBLE, D. M.","u0034749"]],"yea":2001,"sem":8},{"cat":6900,"sec":1,"com":"Lecture","sub":"BIOL","num":3173,"nam":"Tchg Experience","enr":0,"des":"Experience in teaching lecture, laboratory, or discussion sections. Arrangements made through individual course professor.","cap":100,"typ":"In Person","uni":"--","ins":[["WOLSTENHOLME, D. R.","u0029503"]],"yea":2001,"sem":8},{"cat":6921,"sec":1,"com":"Lecture","sub":"BIOL","num":13890,"nam":"Isotopics","enr":0,"des":"Readings and discussions of advanced topics in environmental physiology, physiological ecology, and ecosystem processes, with some emphasis on stable isotope methods.","cap":0,"typ":"In Person","uni":"2.0","req":["Instructor Consent"],"rek":"Yes","yea":2001,"sem":8},{"cat":6921,"sec":2,"com":"Lecture","sub":"BIOL","num":14404,"nam":"Isotopics","enr":12,"des":"Readings and discussions of advanced topics in environmental physiology, physiological ecology, and ecosystem processes, with some emphasis on stable isotope methods.","cap":13,"typ":"In Person","uni":"2.0","ins":[["CERLING, T. E.","u0029442"],["DEARING, M. D.","u0028665"],["EHLERINGER, J. R.","u0034952"]],"req":["Instructor Consent"],"rek":"Yes","yea":2001,"sem":8},{"cat":6950,"sec":1,"com":"Lecture","sub":"BIOL","num":5082,"nam":"Independent Study","enr":0,"des":"Independent study on topics chosen by student by arrangement with individual faculty.","cap":30,"typ":"In Person","uni":"--","ins":[["ADLER, F. R.","u0028684"]],"yea":2001,"sem":8},{"cat":6965,"sec":1,"com":"Lecture","sub":"BIOL","num":10522,"nam":"Topics in Dev Biol","enr":0,"des":"Discussions of current research literature in the development of plants and animals.","cap":30,"typ":"In Person","uni":"--","ins":[["GARD, D. L.","u0034654"]],"req":["Instructor Consent"],"rek":"Yes","yea":2001,"sem":8},{"cat":6970,"sec":1,"com":"Thesis Research","sub":"BIOL","num":3174,"nam":"Thesis Research-Masters","enr":1,"des":"","cap":10,"typ":"In Person","uni":"--","ins":[["PARKINSON JR, J. S.","u0028873"]],"yea":2001,"sem":8},{"cat":7106,"sec":1,"com":"Seminar","sub":"BIOL","num":3175,"nam":"Sem Biochem\/Molec","enr":0,"des":"Techniques of seminar presentation and data analysis, and communication of scientific information per se in area of biochemistry and molecular biology.","cap":10,"typ":"In Person","uni":"--","ins":[["WOLSTENHOLME, D. R.","u0029503"]],"req":["Prerequisite: Graduate standing in Biology or instructor consent."],"rek":"Yes","yea":2001,"sem":8},{"cat":7106,"sec":2,"com":"Seminar","sub":"BIOL","num":10523,"nam":"Sem Biochem\/Molec","enr":0,"des":"Techniques of seminar presentation and data analysis, and communication of scientific information per se in area of biochemistry and molecular biology.","cap":10,"typ":"In Person","uni":"--","ins":[["WOLSTENHOLME, D. R.","u0029503"]],"req":["Prerequisite: Graduate standing in Biology or instructor consent."],"rek":"Yes","yea":2001,"sem":8},{"cat":7206,"sec":1,"com":"Seminar","sub":"BIOL","num":3176,"nam":"Sem Cell\/Devel\/Gen","enr":0,"des":"Techniques of seminar presentation and data analysis and communication of scientific information per se in area of cellular, developmental, and genetic biology.","cap":10,"typ":"In Person","uni":"--","ins":[["WOLSTENHOLME, D. R.","u0029503"]],"req":["Prerequisite: Graduate standing in Biology or instructor consent."],"rek":"Yes","yea":2001,"sem":8},{"cat":7206,"sec":2,"com":"Seminar","sub":"BIOL","num":10524,"nam":"Sem Cell\/Devel\/Gen","enr":0,"des":"Techniques of seminar presentation and data analysis and communication of scientific information per se in area of cellular, developmental, and genetic biology.","cap":10,"typ":"In Person","uni":"--","ins":[["WOLSTENHOLME, D. R.","u0029503"]],"req":["Prerequisite: Graduate standing in Biology or instructor consent."],"rek":"Yes","yea":2001,"sem":8},{"cat":7306,"sec":1,"com":"Seminar","sub":"BIOL","num":9945,"nam":"Sem Organisml\/Phys","enr":0,"des":"Techniques of seminar presentation and data analysis, and communication of scientific information per se in area of organismal and physiology biology.","cap":10,"typ":"In Person","uni":"--","ins":[["WOLSTENHOLME, D. R.","u0029503"]],"req":["Prerequisite: Graduate standing in Biology or instructor consent."],"rek":"Yes","yea":2001,"sem":8},{"cat":7406,"sec":1,"com":"Seminar","sub":"BIOL","num":9946,"nam":"Sem Ecol\/Evol","enr":0,"des":"Techniques of seminar presentation and data analysis, and communication of scientific information per se in area of ecology and evolution.","cap":10,"typ":"In Person","uni":"--","ins":[["WOLSTENHOLME, D. R.","u0029503"]],"req":["Prerequisite: Graduate standing in Biology or instructor consent."],"rek":"Yes","yea":2001,"sem":8},{"cat":7406,"sec":2,"com":"Seminar","sub":"BIOL","num":10525,"nam":"Sem Ecol\/Evol","enr":0,"des":"Techniques of seminar presentation and data analysis, and communication of scientific information per se in area of ecology and evolution.","cap":10,"typ":"In Person","uni":"--","ins":[["WOLSTENHOLME, D. R.","u0029503"]],"req":["Prerequisite: Graduate standing in Biology or instructor consent."],"rek":"Yes","yea":2001,"sem":8},{"cat":7810,"sec":1,"com":"Independent Study","sub":"BIOL","num":6640,"nam":"Research In Progress","enr":0,"des":"Students present progress reports on their reseach and receive critical constructive feedback from two faculty members.","cap":60,"typ":"In Person","uni":"--","ins":[["WOLSTENHOLME, D. R.","u0029503"]],"yea":2001,"sem":8},{"cat":7950,"sec":1,"com":"Lecture","sub":"BIOL","num":9244,"nam":"Independent Study","enr":1,"des":"Independent study on topics chosen by student by arrangement with individual faculty.","cap":15,"typ":"In Person","uni":"--","ins":[["ADLER, F. R.","u0028684"]],"yea":2001,"sem":8},{"cat":7961,"sec":1,"com":"Lecture","sub":"BIOL","num":3177,"nam":"Adv Tpcs: Biochem\/Molec","enr":8,"des":"Topics of special interest taught when justified by student and faculty interest. Content varies from year to year.","cap":10,"typ":"In Person","uni":"--","ins":[["CLAYTON, D. H.","u0029005"]],"yea":2001,"sem":8},{"cat":7962,"sec":1,"com":"Lecture","sub":"BIOL","num":3179,"nam":"Adv Tpcs:Cell\/Devel\/Gen","enr":0,"des":"Topics of special interest taught when justified by student and faculty interest. Content varies from year to year.","cap":10,"typ":"In Person","uni":"--","ins":[["WOLSTENHOLME, D. R.","u0029503"]],"yea":2001,"sem":8},{"cat":7963,"sec":1,"com":"Lecture","sub":"BIOL","num":9419,"nam":"Adv Tpcs:Phys\/Organisml","enr":0,"des":"Topics of special interest taught when justified by student and faculty interest. Content varies from year to year.","cap":20,"typ":"In Person","uni":"--","ins":[["WOLSTENHOLME, D. R.","u0029503"]],"yea":2001,"sem":8},{"cat":7964,"sec":1,"com":"Lecture","sub":"BIOL","num":3180,"nam":"Adv Tpcs: Ecol\/Evol","enr":9,"des":"Topics of special interest taught when justified by student and faculty interest. Content varies from year to year.","cap":10,"typ":"In Person","uni":"--","ins":[["CLAYTON, D. H.","u0029005"]],"yea":2001,"sem":8},{"cat":7970,"sec":1,"com":"Thesis Research","sub":"BIOL","num":3181,"nam":"Thesis Research - Phd","enr":1,"des":"","cap":10,"typ":"In Person","uni":"--","ins":[["PARKINSON JR, J. S.","u0028873"]],"yea":2001,"sem":8},{"cat":7971,"sec":1,"com":"Thesis Research","sub":"BIOL","num":3182,"nam":"Faculty Consultation","enr":0,"des":"","cap":10,"typ":"In Person","uni":"--","ins":[["PARKINSON JR, J. S.","u0028873"]],"yea":2001,"sem":8}]